lamblbs/__init__.py
lamblbs/__main__.py
lamblbs/cmd_utils.py
lamblbs/fs_cmd.py
lamblbs/instance_cmd.py
lamblbs/ssh_cmd.py
lamblbs-2024.2a0.dist-info/LICENSE
lamblbs-2024.2a0.dist-info/METADATA
lamblbs-2024.2a0.dist-info/WHEEL
lamblbs-2024.2a0.dist-info/entry_points.txt
lamblbs-2024.2a0.dist-info/top_level.txt
lamblbs-2024.2a0.dist-info/RECORD
