Metadata-Version: 2.1
Name: lamblbs
Version: 2024.2a0
Summary: Unofficial CLI to manage Lambdalabs Cloud resources such as: instances, ssh keys
Author-email: Fermin Ordaz <fermin.ordaz@gmail.com>
Keywords: lambdalabs
Requires-Python: >=3.8
License-File: LICENSE
Requires-Dist: click
Requires-Dist: requests
